seanalgorithms/__init__.py
seanalgorithms/arrays/__init__.py
seanalgorithms/arrays/delete_nth.py
seanalgorithms/arrays/flatten.py
seanalgorithms/arrays/garage.py
seanalgorithms/arrays/josephus.py
seanalgorithms/arrays/limit.py
seanalgorithms/arrays/longest_non_repeat.py
seanalgorithms/arrays/max_ones_index.py
seanalgorithms/arrays/merge_intervals.py
seanalgorithms/arrays/missing_ranges.py
seanalgorithms/arrays/move_zeros.py
seanalgorithms/arrays/n_sum.py
seanalgorithms/arrays/plus_one.py
seanalgorithms/arrays/rotate.py
seanalgorithms/arrays/summarize_ranges.py
seanalgorithms/arrays/three_sum.py
seanalgorithms/arrays/top_1.py
seanalgorithms/arrays/trimmean.py
seanalgorithms/arrays/two_sum.py
seanalgorithms/backtrack/__init__.py
seanalgorithms/backtrack/add_operators.py
seanalgorithms/backtrack/anagram.py
seanalgorithms/backtrack/array_sum_combinations.py
seanalgorithms/backtrack/combination_sum.py
seanalgorithms/backtrack/factor_combinations.py
seanalgorithms/backtrack/find_words.py
seanalgorithms/backtrack/generate_abbreviations.py
seanalgorithms/backtrack/generate_parenthesis.py
seanalgorithms/backtrack/letter_combination.py
seanalgorithms/backtrack/palindrome_partitioning.py
seanalgorithms/backtrack/pattern_match.py
seanalgorithms/backtrack/permute.py
seanalgorithms/backtrack/permute_unique.py
seanalgorithms/backtrack/subsets.py
seanalgorithms/backtrack/subsets_unique.py
seanalgorithms/backtrack/subsets_v2.py
seanalgorithms/bfs/__init__.py
seanalgorithms/bfs/maze_search.py
seanalgorithms/bfs/shortest_distance_from_all_buildings.py
seanalgorithms/bfs/word_ladder.py
seanalgorithms/bit/__init__.py
seanalgorithms/bit/add_bitwise_operator.py
seanalgorithms/bit/binary_gap.py
seanalgorithms/bit/bit_operation.py
seanalgorithms/bit/bytes_int_conversion.py
seanalgorithms/bit/count_flips_to_convert.py
seanalgorithms/bit/count_ones.py
seanalgorithms/bit/find_difference.py
seanalgorithms/bit/find_missing_number.py
seanalgorithms/bit/flip_bit_longest_sequence.py
seanalgorithms-0.8.dist-info/LICENSE
seanalgorithms-0.8.dist-info/METADATA
seanalgorithms-0.8.dist-info/WHEEL
seanalgorithms-0.8.dist-info/top_level.txt
seanalgorithms-0.8.dist-info/RECORD
