Metadata-Version: 2.1
Name: seanalgorithms
Version: 0.8
Summary: Python algorithms
Home-page: https://github.com/seanlab3/algorithms
Author: seanlab
Author-email: seanlabcoding33@gmail.com
License: UNKNOWN
Platform: UNKNOWN
Classifier: License :: OSI Approved :: MIT License
License-File: LICENSE
Requires-Dist: cython
